napari_simple_orthoviewer/__init__.py
napari_simple_orthoviewer/_version.py
napari_simple_orthoviewer/_widget.py
napari_simple_orthoviewer/napari.yaml
napari_simple_orthoviewer/_tests/__init__.py
napari_simple_orthoviewer/_tests/test_widget.py
napari_simple_orthoviewer-0.0.5.dist-info/LICENSE
napari_simple_orthoviewer-0.0.5.dist-info/METADATA
napari_simple_orthoviewer-0.0.5.dist-info/WHEEL
napari_simple_orthoviewer-0.0.5.dist-info/entry_points.txt
napari_simple_orthoviewer-0.0.5.dist-info/top_level.txt
napari_simple_orthoviewer-0.0.5.dist-info/RECORD
