Metadata-Version: 2.1
Name: napari-simple-orthoviewer
Version: 0.0.5
Summary: A simple orthogonal viewer in napari
Author: Krishnan Venkataraman
Author-email: krishvraman95@gmail.com
License: 
Project-URL: Bug Tracker, https://github.com/Krishvraman/napari-simple-orthoviewer/issues
Project-URL: Documentation, https://github.com/Krishvraman/napari-simple-orthoviewer#README.md
Project-URL: Source Code, https://github.com/Krishvraman/napari-simple-orthoviewer
Project-URL: User Support, https://github.com/Krishvraman/napari-simple-orthoviewer/issues
Classifier: Development Status :: 2 - Pre-Alpha
Classifier: Framework :: napari
Classifier: Intended Audience :: Developers
Classifier: License :: OSI Approved :: BSD License
Classifier: Operating System :: OS Independent
Classifier: Programming Language :: Python
Classifier: Programming Language :: Python :: 3
Classifier: Programming Language :: Python :: 3 :: Only
Classifier: Programming Language :: Python :: 3.9
Classifier: Programming Language :: Python :: 3.10
Classifier: Programming Language :: Python :: 3.11
Classifier: Programming Language :: Python :: 3.12
Classifier: Topic :: Scientific/Engineering :: Image Processing
Requires-Python: >=3.9
License-File: LICENSE
Requires-Dist: numpy
Requires-Dist: magicgui
Requires-Dist: qtpy
Requires-Dist: matplotlib
Requires-Dist: tifffile
Requires-Dist: napari
Provides-Extra: testing
Requires-Dist: tox; extra == "testing"
Requires-Dist: pytest; extra == "testing"
Requires-Dist: pytest-cov; extra == "testing"
Requires-Dist: pytest-qt; extra == "testing"
Requires-Dist: napari; extra == "testing"
Requires-Dist: pyqt5; extra == "testing"
